{
    "status": "success",
    "code": 0,
    "exception": "",
    "response": {
        "status": 0,
        "task_start": "2020-08-27 16:13:44",
        "task_end": "2020-08-27 16:13:49",
        "result": [
            {
                "status": 0,
                "query": {
                    "type": 1,
                    "params": {
                        "region": "10",
                        "firstname": "АЛЕКСЕЙ",
                        "lastname": "НИКИТИН"
                    }
                },
                "result": [
                    {
                        "name": "НИКИТИН АЛЕКСЕЙ АЛЕКСАНДРОВИЧ 28.10.1976 185000, РОССИЯ, Г. ПЕТРОЗАВОДСК",
                        "exe_production": "84852/16/10001-ИП от 18.11.2016 16746/17/10001-СД",
                        "details": "Судебный приказ от 22.08.2016 № СП2-2435/2016-6 СУДЕБНЫЙ УЧАСТОК № 6 Г. ПЕТРОЗАВОДСКА",
                        "subject": "Задолженность по кредитным платежам (кроме ипотеки): 25090.04 руб.",
                        "department": "ОСП по работе с физическими лицами №1 г.Петрозаводска и Прионежского района 185910, Республика Карелия, г.Петрозаводск, ул.Красная, д.33",
                        "bailiff": "АККОЛАЙНЕН Д. Г. +7(8142)78-39-63<br>+7(8142)78-49-39<br>+7(8142)76-05-55",
                        "ip_end": ""
                    },
                    {
                        "name": "НИКИТИН АЛЕКСЕЙ АЛЕКСАНДРОВИЧ 28.10.1976 185000, РОССИЯ, Г. ПЕТРОЗАВОДСК",
                        "exe_production": "16746/17/10001-ИП от 27.03.2017 16746/17/10001-СД",
                        "details": "Исполнительный лист от 10.03.2017 № ФС013953215 ПЕТРОЗАВОДСКИЙ ГОРОДСКОЙ СУД",
                        "subject": "Иные взыскания имущественного характера не в бюджеты РФ: 300 руб.",
                        "department": "ОСП по работе с физическими лицами №1 г.Петрозаводска и Прионежского района 185910, Республика Карелия, г.Петрозаводск, ул.Красная, д.33",
                        "bailiff": "АККОЛАЙНЕН Д. Г. +7(8142)78-39-63<br>+7(8142)78-49-39<br>+7(8142)76-05-55",
                        "ip_end": ""
                    },
                    {
                        "name": "НИКИТИН АЛЕКСЕЙ АЛЕКСЕЕВИЧ 27.05.1989 185000, РОССИЯ, Г. ПЕТРОЗАВОДСК",
                        "exe_production": "54440/17/10001-ИП от 19.09.2014",
                        "details": "Акт по делу об административном правонарушении от 11.06.2014 № 5-401/2014-2 СУДЕБНЫЙ УЧАСТОК № 2 Г. ПЕТРОЗАВОДСКА",
                        "subject": "Административное наказание в виде обязательных работ",
                        "department": "ОСП по работе с физическими лицами №1 г.Петрозаводска и Прионежского района 185910, Республика Карелия, г.Петрозаводск, ул.Красная, д.33",
                        "bailiff": "КУВШИНОВА И. В. +7(8142)78-39-63<br>+7(8142)78-49-39<br>+7(8142)76-05-55",
                        "ip_end": ""
                    },
                    {
                        "name": "НИКИТИН АЛЕКСЕЙ ВЛАДИМИРОВИЧ 26.07.1971",
                        "exe_production": "100714/17/10001-ИП от 07.12.2017 100714/17/10001-СД",
                        "details": "Судебный приказ от 23.08.2016 № СП2-2874/16-14 СУДЕБНЫЙ УЧАСТОК № 14 Г. ПЕТРОЗАВОДСКА",
                        "subject": "Транспортный налог: 3267.06 руб.",
                        "department": "ОСП по работе с физическими лицами №1 г.Петрозаводска и Прионежского района 185910, Республика Карелия, г.Петрозаводск, ул.Красная, д.33",
                        "bailiff": "ШАТАЛОВА Т. П. +7(8142)76-88-97<br>+7(8142)78-49-39<br>+7(8142)76-05-55",
                        "ip_end": ""
                    },
                    {
                        "name": "НИКИТИН АЛЕКСЕЙ АЛЕКСАНДРОВИЧ 28.10.1976 РОССИЯ, ПЕТРОЗАВОДСК",
                        "exe_production": "26090/18/10001-ИП от 26.03.2018 16746/17/10001-СД",
                        "details": "Судебный приказ от 12.09.2017 № СП 2А-3231/2017-6 СУДЕБНЫЙ УЧАСТОК № 6 Г. ПЕТРОЗАВОДСКА",
                        "subject": "Взыскание налогов и сборов, включая пени: 2209.4 руб.",
                        "department": "ОСП по работе с физическими лицами №1 г.Петрозаводска и Прионежского района 185910, Республика Карелия, г.Петрозаводск, ул.Красная, д.33",
                        "bailiff": "АККОЛАЙНЕН Д. Г. +7(8142)78-39-63<br>+7(8142)78-49-39<br>+7(8142)76-05-55",
                        "ip_end": ""
                    },
                    {
                        "name": "НИКИТИН АЛЕКСЕЙ ВЛАДИМИРОВИЧ 26.07.1971 185000, РОССИЯ, Г. ПЕТРОЗАВОДСК",
                        "exe_production": "26197/17/10001-ИП от 03.05.2017",
                        "details": "Исполнительный лист от 23.08.2016 № ВС075701075 СУДЕБНЫЙ УЧАСТОК № 14 Г. ПЕТРОЗАВОДСКА",
                        "subject": "",
                        "department": "ОСП по работе с физическими лицами №1 г.Петрозаводска и Прионежского района 185910, Республика Карелия, г.Петрозаводск, ул.Красная, д.33",
                        "bailiff": "ГАРАЖА Л. А. +7(8142)78-40-44<br>+7(8142)78-49-39<br>+7(8142)76-05-55",
                        "ip_end": "2017-10-13, 46, 1, 4"
                    },
                    {
                        "name": "НИКИТИН АЛЕКСЕЙ АЛЕКСАНДРОВИЧ 28.10.1976 Г. ПЕТРОЗАВОДСК",
                        "exe_production": "1408/19/10001-ИП от 11.01.2019 16746/17/10001-СД",
                        "details": "Исполнительный лист от 12.09.2017 № ВС081489888 СУДЕБНЫЙ УЧАСТОК № 6 Г. ПЕТРОЗАВОДСКА",
                        "subject": "Госпошлина, присужденная судом: 165.72 руб.",
                        "department": "ОСП по работе с физическими лицами №1 г.Петрозаводска и Прионежского района 185910, Республика Карелия, г.Петрозаводск, ул.Красная, д.33",
                        "bailiff": "АККОЛАЙНЕН Д. Г. +7(8142)78-39-63<br>+7(8142)78-49-39<br>+7(8142)76-05-55",
                        "ip_end": ""
                    },
                    {
                        "name": "НИКИТИН АЛЕКСЕЙ ВЛАДИМИРОВИЧ 26.07.1971",
                        "exe_production": "35662/19/10001-ИП от 03.04.2019",
                        "details": "Судебный приказ от 03.09.2018 № СП-2949/2018-5 СУДЕБНЫЙ УЧАСТОК № 5 Г. ПЕТРОЗАВОДСКА",
                        "subject": "Задолженность по платежам за жилую площадь, коммунальные платежи, включая пени",
                        "department": "ОСП по работе с физическими лицами №1 г.Петрозаводска и Прионежского района 185910, Республика Карелия, г.Петрозаводск, ул.Красная, д.33",
                        "bailiff": "ДАНИЛЕВСКАЯ О. Г. +7(8142)76-33-63<br>+7(8142)78-49-39<br>+7(8142)76-05-55",
                        "ip_end": "2019-06-28, 46, 1, 4"
                    },
                    {
                        "name": "НИКИТИН АЛЕКСЕЙ ВЛАДИМИРОВИЧ 26.07.1971",
                        "exe_production": "38639/19/10001-ИП от 10.04.2019 100714/17/10001-СД",
                        "details": "Судебный приказ от 19.02.2019 № СП2-6830/2018-5 СУДЕБНЫЙ УЧАСТОК № 5 Г. ПЕТРОЗАВОДСКА",
                        "subject": "Задолженность по платежам за газ, тепло и электроэнергию: 17419.57 руб.",
                        "department": "ОСП по работе с физическими лицами №1 г.Петрозаводска и Прионежского района 185910, Республика Карелия, г.Петрозаводск, ул.Красная, д.33",
                        "bailiff": "ШАТАЛОВА Т. П. +7(8142)76-88-97<br>+7(8142)78-49-39<br>+7(8142)76-05-55",
                        "ip_end": ""
                    },
                    {
                        "name": "НИКИТИН АЛЕКСЕЙ ВЛАДИМИРОВИЧ 26.07.1971",
                        "exe_production": "42064/19/10001-ИП от 18.04.2019 100714/17/10001-СД",
                        "details": "Судебный приказ от 04.05.2018 № СП2-1500/2018-14 СУДЕБНЫЙ УЧАСТОК № 14 Г. ПЕТРОЗАВОДСКА",
                        "subject": "Задолженность по платежам за жилую площадь, коммунальные платежи, включая пени: 7873.34 руб.",
                        "department": "ОСП по работе с физическими лицами №1 г.Петрозаводска и Прионежского района 185910, Республика Карелия, г.Петрозаводск, ул.Красная, д.33",
                        "bailiff": "ШАТАЛОВА Т. П. +7(8142)76-88-97<br>+7(8142)78-49-39<br>+7(8142)76-05-55",
                        "ip_end": ""
                    },
                    {
                        "name": "НИКИТИН АЛЕКСЕЙ ВЛАДИМИРОВИЧ 26.07.1971",
                        "exe_production": "45623/19/10001-ИП от 25.04.2019",
                        "details": "Судебный приказ от 17.07.2018 № СП2-1914/2018-5 СУДЕБНЫЙ УЧАСТОК № 5 Г. ПЕТРОЗАВОДСКА",
                        "subject": "Задолженность по платежам за жилую площадь, коммунальные платежи, включая пени",
                        "department": "ОСП по работе с физическими лицами №1 г.Петрозаводска и Прионежского района 185910, Республика Карелия, г.Петрозаводск, ул.Красная, д.33",
                        "bailiff": "ДАНИЛЕВСКАЯ О. Г. +7(8142)76-33-63<br>+7(8142)78-49-39<br>+7(8142)76-05-55",
                        "ip_end": "2019-06-28, 46, 1, 4"
                    },
                    {
                        "name": "НИКИТИН АЛЕКСЕЙ ВЛАДИМИРОВИЧ 26.07.1971",
                        "exe_production": "119936/19/10001-ИП от 01.10.2019 100714/17/10001-СД",
                        "details": "Судебный приказ от 09.07.2019 № СП2-2804/2019-5 СУДЕБНЫЙ УЧАСТОК № 5 Г. ПЕТРОЗАВОДСКА",
                        "subject": "Задолженность по платежам за жилую площадь, коммунальные платежи, включая пени: 735.42 руб.",
                        "department": "ОСП по работе с физическими лицами №1 г.Петрозаводска и Прионежского района 185910, Республика Карелия, г.Петрозаводск, ул.Красная, д.33",
                        "bailiff": "ШАТАЛОВА Т. П. +7(8142)76-88-97<br>+7(8142)78-49-39<br>+7(8142)76-05-55",
                        "ip_end": ""
                    },
                    {
                        "name": "НИКИТИН АЛЕКСЕЙ АЛЕКСАНДРОВИЧ 28.10.1976 Г. ПЕТРОЗАВОДСК",
                        "exe_production": "169167/19/10001-ИП от 25.12.2019 16746/17/10001-СД",
                        "details": "Акт по делу об административном правонарушении от 27.11.2018 № 32210001180004273013 ОСП ПО РАБОТЕ С ФИЗИЧЕСКИМИ ЛИЦАМИ № 1 Г. ПЕТРОЗАВОДСКА И ПРИОНЕЖСКОГО РАЙОНА УФССП ПО РЕСПУБЛИКЕ КАРЕЛИЯ",
                        "subject": "Штраф по постановлению должностного лица ФССП России Штраф СПИ: 977.34 руб.",
                        "department": "ОСП по работе с физическими лицами №1 г.Петрозаводска и Прионежского района 185910, Республика Карелия, г.Петрозаводск, ул.Красная, д.33",
                        "bailiff": "АККОЛАЙНЕН Д. Г. +7(8142)78-39-63<br>+7(8142)78-49-39<br>+7(8142)76-05-55",
                        "ip_end": ""
                    },
                    {
                        "name": "НИКИТИН АЛЕКСЕЙ ВЛАДИМИРОВИЧ 26.07.1971",
                        "exe_production": "140887/19/10001-ИП от 06.11.2019 100714/17/10001-СД",
                        "details": "Судебный приказ от 07.09.2019 № СП-4106/2019-5 СУДЕБНЫЙ УЧАСТОК № 5 Г. ПЕТРОЗАВОДСКА",
                        "subject": "Задолженность по платежам за жилую площадь, коммунальные платежи, включая пени: 4914.79 руб.",
                        "department": "ОСП по работе с физическими лицами №1 г.Петрозаводска и Прионежского района 185910, Республика Карелия, г.Петрозаводск, ул.Красная, д.33",
                        "bailiff": "ШАТАЛОВА Т. П. +7(8142)76-88-97<br>+7(8142)78-49-39<br>+7(8142)76-05-55",
                        "ip_end": ""
                    },
                    {
                        "name": "НИКИТИН АЛЕКСЕЙ ВЛАДИМИРОВИЧ 26.07.1971 РЕСП. КАРЕЛИЯ, Г. ПЕТРОЗАВОДСК",
                        "exe_production": "48534/20/10001-ИП от 25.05.2020 48532/20/10001-СВ",
                        "details": "Судебный приказ от 26.02.2020 № СП-631/2020-5 СУДЕБНЫЙ УЧАСТОК № 14 Г. ПЕТРОЗАВОДСКА",
                        "subject": "Задолженность по платежам за жилую площадь, коммунальные платежи, включая пени: 6095.15 руб.",
                        "department": "ОСП по работе с физическими лицами №1 г.Петрозаводска и Прионежского района 185910, Республика Карелия, г.Петрозаводск, ул.Красная, д.33",
                        "bailiff": "ШАТАЛОВА Т. П. +7(8142)76-88-97<br>+7(8142)78-49-39<br>+7(8142)76-05-55",
                        "ip_end": ""
                    },
                    {
                        "name": "НИКИТИН АЛЕКСЕЙ АЛЕКСАНДРОВИЧ 28.10.1976 Г. ПЕТРОЗАВОДСК",
                        "exe_production": "51803/20/10001-ИП от 28.05.2020",
                        "details": "Судебный приказ от 24.03.2020 № СП-755/2020-6 СУДЕБНЫЙ УЧАСТОК № 6 Г. ПЕТРОЗАВОДСКА",
                        "subject": "Задолженность по кредитным платежам (кроме ипотеки): 9318.52 руб.",
                        "department": "ОСП по работе с физическими лицами №1 г.Петрозаводска и Прионежского района 185910, Республика Карелия, г.Петрозаводск, ул.Красная, д.33",
                        "bailiff": "АККОЛАЙНЕН Д. Г. +7(8142)78-39-63<br>+7(8142)78-49-39<br>+7(8142)76-05-55",
                        "ip_end": ""
                    },
                    {
                        "name": "НИКИТИН АЛЕКСЕЙ ВИТАЛЬЕВИЧ 16.05.1995 ВОЛОГОДСКАЯ ОБЛ.",
                        "exe_production": "53550/20/10001-ИП от 02.06.2020",
                        "details": "Исполнительный лист от 18.05.2020 № ВС 085322940 СУДЕБНЫЙ УЧАСТОК № 5 Г. ПЕТРОЗАВОДСКА",
                        "subject": "Иные взыскания имущественного характера в пользу бюджетов Российской Федерации: 13707.97 руб.",
                        "department": "ОСП по работе с физическими лицами №1 г.Петрозаводска и Прионежского района 185910, Республика Карелия, г.Петрозаводск, ул.Красная, д.33",
                        "bailiff": "КУВШИНОВА И. В. +7(8142)78-39-63<br>+7(8142)78-49-39<br>+7(8142)76-05-55",
                        "ip_end": ""
                    },
                    {
                        "name": "НИКИТИН АЛЕКСЕЙ ВЛАДИМИРОВИЧ 26.07.1971 РЕСП. КАРЕЛИЯ, Г. ПЕТРОЗАВОДСК",
                        "exe_production": "66262/20/10001-ИП от 30.06.2020",
                        "details": "Судебный приказ от 11.04.2020 № СП-1942/2020-5 СУДЕБНЫЙ УЧАСТОК № 5 Г. ПЕТРОЗАВОДСКА",
                        "subject": "Задолженность по платежам за газ, тепло и электроэнергию: 14269.51 руб.",
                        "department": "ОСП по работе с физическими лицами №1 г.Петрозаводска и Прионежского района 185910, Республика Карелия, г.Петрозаводск, ул.Красная, д.33",
                        "bailiff": "ШАТАЛОВА Т. П. +7(8142)76-88-97<br>+7(8142)78-49-39<br>+7(8142)76-05-55",
                        "ip_end": ""
                    },
                    {
                        "name": "НИКИТИН АЛЕКСЕЙ ПЕТРОВИЧ 30.05.1975 РЕСПУБЛИКА КАРЕЛИЯ",
                        "exe_production": "100447/20/10020-ИП от 13.07.2020",
                        "details": "Акт по делу об административном правонарушении от 23.04.2020 № 18810010200000197576 ОБДПС УМВД РОССИИ ПО Г. ПЕТРОЗАВОДСКУ",
                        "subject": "Штраф ГИБДД: 500 руб.",
                        "department": "ОСП по работе с физическими лицами №2 г.Петрозаводска 185910, Республика Карелия, г.Петрозаводск, ул.Красная, д.33",
                        "bailiff": "ПОВЕЛИХИНА Н. П. +7(8142)76-38-11<br>+7(8142)76-08-74<br>+7(8142)76-05-55",
                        "ip_end": ""
                    },
                    {
                        "name": "НИКИТИН АЛЕКСЕЙ ВЛАДИМИРОВИЧ 26.07.1971 РОССИЯ, Г. ПЕТРОЗАВОДСК",
                        "exe_production": "25572/16/10020-ИП от 20.02.2014 17036/18/10020-СД",
                        "details": "Судебный приказ от 14.10.2013 № СП2-2471/2013-14 Постановление о взыскании исполнительского сбора МИРОВОЙ СУДЬЯ С/У № 14 Г. ПЕТРОЗАВОДСКА РК",
                        "subject": "Задолженность по кредитным платежам (кроме ипотеки): 219330.54 руб. Исполнительский сбор: 19273.13 руб.",
                        "department": "ОСП по работе с физическими лицами №2 г.Петрозаводска 185910, Республика Карелия, г.Петрозаводск, ул.Красная, д.33",
                        "bailiff": "ФЕСЕНКО В. М. +7(8142)76-05-93<br>+7(8142)76-08-74<br>+7(8142)76-05-55",
                        "ip_end": ""
                    },
                    {
                        "name": "НИКИТИН АЛЕКСЕЙ ВЛАДИМИРОВИЧ 06.11.1974",
                        "exe_production": "32898/16/10020-ИП от 13.05.2016",
                        "details": "Судебный приказ от 11.12.2015 № СП-3146/2015-2 СУДЕБНЫЙ УЧАСТОК № 2 Г. ПЕТРОЗАВОДСКА",
                        "subject": "Задолженность по платежам за газ, тепло и электроэнергию",
                        "department": "ОСП по работе с физическими лицами №2 г.Петрозаводска 185910, Республика Карелия, г.Петрозаводск, ул.Красная, д.33",
                        "bailiff": "ЗАПОЛЬСКАЯ М. А. +7(8142)78-51-45<br>+7(8142)76-08-74<br>+7(8142)76-05-55",
                        "ip_end": "2017-11-29, 46, 1, 4"
                    },
                    {
                        "name": "НИКИТИН АЛЕКСЕЙ ВЛАДИМИРОВИЧ 06.11.1974",
                        "exe_production": "51075/16/10020-ИП от 05.07.2016",
                        "details": "Судебный приказ от 09.06.2012 № СП2-608/2012-2 СУДЕБНЫЙ УЧАСТОК № 2 Г. ПЕТРОЗАВОДСКА",
                        "subject": "Задолженность по платежам за жилую площадь, коммунальные платежи, включая пени",
                        "department": "ОСП по работе с физическими лицами №2 г.Петрозаводска 185910, Республика Карелия, г.Петрозаводск, ул.Красная, д.33",
                        "bailiff": "ЗАПОЛЬСКАЯ М. А. +7(8142)78-51-45<br>+7(8142)76-08-74<br>+7(8142)76-05-55",
                        "ip_end": "2017-11-29, 46, 1, 4"
                    },
                    {
                        "name": "НИКИТИН АЛЕКСЕЙ ВЛАДИМИРОВИЧ 06.11.1974",
                        "exe_production": "67889/16/10020-ИП от 23.09.2016",
                        "details": "Судебный приказ от 11.07.2016 № СП2-1792/2016-2 СУДЕБНЫЙ УЧАСТОК № 2 Г. ПЕТРОЗАВОДСКА",
                        "subject": "Задолженность по платежам за газ, тепло и электроэнергию",
                        "department": "ОСП по работе с физическими лицами №2 г.Петрозаводска 185910, Республика Карелия, г.Петрозаводск, ул.Красная, д.33",
                        "bailiff": "ЗАПОЛЬСКАЯ М. А. +7(8142)78-51-45<br>+7(8142)76-08-74<br>+7(8142)76-05-55",
                        "ip_end": "2017-11-29, 46, 1, 4"
                    },
                    {
                        "name": "НИКИТИН АЛЕКСЕЙ ВЛАДИМИРОВИЧ 06.11.1974",
                        "exe_production": "29766/17/10020-ИП от 06.05.2017",
                        "details": "Судебный приказ от 30.01.2017 № СП2-5089/2016-2 СУДЕБНЫЙ УЧАСТОК № 2 Г. ПЕТРОЗАВОДСКА",
                        "subject": "Задолженность по платежам за жилую площадь, коммунальные платежи, включая пени",
                        "department": "ОСП по работе с физическими лицами №2 г.Петрозаводска 185910, Республика Карелия, г.Петрозаводск, ул.Красная, д.33",
                        "bailiff": "ЗАПОЛЬСКАЯ М. А. +7(8142)78-51-45<br>+7(8142)76-08-74<br>+7(8142)76-05-55",
                        "ip_end": "2017-11-29, 46, 1, 4"
                    },
                    {
                        "name": "НИКИТИН АЛЕКСЕЙ ВЛАДИМИРОВИЧ 06.11.1974 Г. ПЕТРОЗАВОДСК",
                        "exe_production": "34520/17/10020-ИП от 29.05.2017",
                        "details": "Акт по делу об административном правонарушении от 11.03.2017 № 18880310172510000897 ОП № 1 УМВД РОССИИ ПО Г. ПЕТРОЗАВОДСКУ",
                        "subject": "Иной штраф ОВД",
                        "department": "ОСП по работе с физическими лицами №2 г.Петрозаводска 185910, Республика Карелия, г.Петрозаводск, ул.Красная, д.33",
                        "bailiff": "ЗАПОЛЬСКАЯ М. А. +7(8142)78-51-45<br>+7(8142)76-08-74<br>+7(8142)76-05-55",
                        "ip_end": "2017-11-29, 46, 1, 4"
                    },
                    {
                        "name": "НИКИТИН АЛЕКСЕЙ НИКОЛАЕВИЧ 02.02.1982",
                        "exe_production": "64319/17/10020-ИП от 23.08.2017",
                        "details": "Судебный приказ от 20.09.2016 № СП2-3166/2016-2 СУДЕБНЫЙ УЧАСТОК № 2 Г. ПЕТРОЗАВОДСКА",
                        "subject": "Взыскание налогов и сборов, включая пени",
                        "department": "ОСП по работе с физическими лицами №2 г.Петрозаводска 185910, Республика Карелия, г.Петрозаводск, ул.Красная, д.33",
                        "bailiff": "ОМЕЛЬКИНА О. Н. +7(8142)76-56-59<br>+7(8142)76-08-74<br>+7(8142)76-05-55",
                        "ip_end": "2017-09-19, 46, 1, 4"
                    },
                    {
                        "name": "НИКИТИН АЛЕКСЕЙ ВЛАДИМИРОВИЧ 06.11.1974 Г. ПЕТРОЗАВОДСК",
                        "exe_production": "66560/17/10020-ИП от 28.08.2017",
                        "details": "Судебный приказ от 26.05.2017 № СП2-1230/2017-2 СУДЕБНЫЙ УЧАСТОК № 2 Г. ПЕТРОЗАВОДСКА",
                        "subject": "Задолженность по платежам за жилую площадь, коммунальные платежи, включая пени",
                        "department": "ОСП по работе с физическими лицами №2 г.Петрозаводска 185910, Республика Карелия, г.Петрозаводск, ул.Красная, д.33",
                        "bailiff": "ЗАПОЛЬСКАЯ М. А. +7(8142)78-51-45<br>+7(8142)76-08-74<br>+7(8142)76-05-55",
                        "ip_end": "2017-11-29, 46, 1, 4"
                    },
                    {
                        "name": "НИКИТИН АЛЕКСЕЙ ИВАНОВИЧ 24.05.1983 РЕСП. КАРЕЛИЯ, КОНДОПОЖСКИЙ Р-Н, С. КОНЧЕЗЕРО",
                        "exe_production": "80819/17/10020-ИП от 18.10.2017",
                        "details": "Акт по делу об административном правонарушении от 01.03.2017 № 5-273/17-10 СУДЕБНЫЙ УЧАСТОК № 10 Г. ПЕТРОЗАВОДСКА",
                        "subject": "Штраф как вид наказания по делам об АП, назначенный судом (за исключением дел по протоколам ФССП)",
                        "department": "ОСП по работе с физическими лицами №2 г.Петрозаводска 185910, Республика Карелия, г.Петрозаводск, ул.Красная, д.33",
                        "bailiff": "КОППАЛОВА О. А. +7(8142)76-93-95<br>+7(8142)76-08-74<br>+7(8142)76-05-55",
                        "ip_end": "2017-12-13, 46, 1, 4"
                    },
                    {
                        "name": "НИКИТИН АЛЕКСЕЙ АЛЕКСАНДРОВИЧ 28.10.1976 Г. ПЕТРОЗАВОДСК",
                        "exe_production": "17036/18/10020-ИП от 01.03.2018",
                        "details": "Исполнительный лист от 20.02.2018 № ВС 078744333 СУДЕБНЫЙ УЧАСТОК № 2 Г. ПЕТРОЗАВОДСКА",
                        "subject": "Госпошлина, присужденная судом: 17473.61 руб.",
                        "department": "ОСП по работе с физическими лицами №2 г.Петрозаводска 185910, Республика Карелия, г.Петрозаводск, ул.Красная, д.33",
                        "bailiff": "ФЕСЕНКО В. М. +7(8142)76-05-93<br>+7(8142)76-08-74<br>+7(8142)76-05-55",
                        "ip_end": ""
                    },
                    {
                        "name": "НИКИТИН АЛЕКСЕЙ АЛЕКСАНДРОВИЧ 28.10.1976 Г. ПЕТРОЗАВОДСК",
                        "exe_production": "30557/18/10020-ИП от 29.03.2018",
                        "details": "Исполнительный лист от 20.02.2018 № ВС078744332 СУДЕБНЫЙ УЧАСТОК № 3 Г. ПЕТРОЗАВОДСКА",
                        "subject": "Иные взыскания имущественного характера не в бюджеты РФ: 575787.16 руб.",
                        "department": "ОСП по работе с физическими лицами №2 г.Петрозаводска 185910, Республика Карелия, г.Петрозаводск, ул.Красная, д.33",
                        "bailiff": "ФЕСЕНКО В. М. +7(8142)76-05-93<br>+7(8142)76-08-74<br>+7(8142)76-05-55",
                        "ip_end": ""
                    },
                    {
                        "name": "НИКИТИН АЛЕКСЕЙ НИКОЛАЕВИЧ 02.02.1982 Г. ПЕТРОЗАВОДСК",
                        "exe_production": "63506/18/10020-ИП от 05.07.2018",
                        "details": "Судебный приказ от 10.01.2014 № 2-5643-13-8 СУДЕБНЫЙ УЧАСТОК № 8 СЕВЕРОДВИНСКОГО СУДЕБНОГО РАЙОНА АРХАНГЕЛЬСКОЙ ОБЛАСТИ",
                        "subject": "Задолженность по кредитным платежам (кроме ипотеки)",
                        "department": "ОСП по работе с физическими лицами №2 г.Петрозаводска 185910, Республика Карелия, г.Петрозаводск, ул.Красная, д.33",
                        "bailiff": "ОМЕЛЬКИНА О. Н. +7(8142)76-56-59<br>+7(8142)76-08-74<br>+7(8142)76-05-55",
                        "ip_end": "2018-07-30, 46, 1, 4"
                    },
                    {
                        "name": "НИКИТИН АЛЕКСЕЙ ВЛАДИМИРОВИЧ 06.11.1974 185000, РОССИЯ, Г. ПЕТРОЗАВОДСК",
                        "exe_production": "9721/19/10020-ИП от 01.02.2019 9272/20/10020-СД",
                        "details": "Судебный приказ от 10.01.2019 № СП2-5277/2018-2 СУДЕБНЫЙ УЧАСТОК № 2 Г. ПЕТРОЗАВОДСКА",
                        "subject": "Задолженность по платежам за жилую площадь, коммунальные платежи, включая пени: 11652.07 руб.",
                        "department": "ОСП по работе с физическими лицами №2 г.Петрозаводска 185910, Республика Карелия, г.Петрозаводск, ул.Красная, д.33",
                        "bailiff": "ЗВУКОВА М. Д. +7(8142)76-08-74<br>+7(8142)76-08-74<br>+7(8142)76-05-55",
                        "ip_end": ""
                    },
                    {
                        "name": "НИКИТИН АЛЕКСЕЙ НИКОЛАЕВИЧ 02.02.1982 Г. ПЕТРОЗАВОДСК",
                        "exe_production": "104755/18/10020-ИП от 01.11.2018",
                        "details": "Судебный приказ от 10.01.2014 № 2-5643-13-8 СУДЕБНЫЙ УЧАСТОК № 4 Г. ПЕТРОЗАВОДСКА",
                        "subject": "Задолженность по кредитным платежам (кроме ипотеки)",
                        "department": "ОСП по работе с физическими лицами №2 г.Петрозаводска 185910, Республика Карелия, г.Петрозаводск, ул.Красная, д.33",
                        "bailiff": "ОМЕЛЬКИНА О. Н. +7(8142)76-56-59<br>+7(8142)76-08-74<br>+7(8142)76-05-55",
                        "ip_end": "2018-11-21, 46, 1, 4"
                    },
                    {
                        "name": "НИКИТИН АЛЕКСЕЙ ВЛАДИМИРОВИЧ 06.11.1974 Г. ПЕТРОЗАВОДСК",
                        "exe_production": "70656/19/10020-ИП от 22.05.2019 9272/20/10020-СД",
                        "details": "Судебный приказ от 23.08.2016 № СП2-1792/2016-2 СУДЕБНЫЙ УЧАСТОК № 2 Г. ПЕТРОЗАВОДСКА",
                        "subject": "Задолженность по платежам за газ, тепло и электроэнергию: 28149.49 руб.",
                        "department": "ОСП по работе с физическими лицами №2 г.Петрозаводска 185910, Республика Карелия, г.Петрозаводск, ул.Красная, д.33",
                        "bailiff": "ЗВУКОВА М. Д. +7(8142)76-08-74<br>+7(8142)76-08-74<br>+7(8142)76-05-55",
                        "ip_end": ""
                    },
                    {
                        "name": "НИКИТИН АЛЕКСЕЙ ВЛАДИМИРОВИЧ 06.11.1974 Г. ПЕТРОЗАВОДСК",
                        "exe_production": "78178/19/10020-ИП от 29.05.2019 9272/20/10020-СД",
                        "details": "Судебный приказ от 16.04.2019 № СП2-722/2019-3 СУДЕБНЫЙ УЧАСТОК № 3 Г. ПЕТРОЗАВОДСКА",
                        "subject": "Задолженность по кредитным платежам (кроме ипотеки): 3380 руб.",
                        "department": "ОСП по работе с физическими лицами №2 г.Петрозаводска 185910, Республика Карелия, г.Петрозаводск, ул.Красная, д.33",
                        "bailiff": "ЗВУКОВА М. Д. +7(8142)76-08-74<br>+7(8142)76-08-74<br>+7(8142)76-05-55",
                        "ip_end": ""
                    },
                    {
                        "name": "НИКИТИН АЛЕКСЕЙ ВЛАДИМИРОВИЧ 06.11.1974 Г. ПЕТРОЗАВОДСК",
                        "exe_production": "83455/19/10020-ИП от 10.06.2019 9272/20/10020-СД",
                        "details": "Судебный приказ от 10.07.2012 № СП2-608/2012-2 СУДЕБНЫЙ УЧАСТОК № 2 Г. ПЕТРОЗАВОДСКА",
                        "subject": "Задолженность по платежам за жилую площадь, коммунальные платежи, включая пени: 25599.16 руб.",
                        "department": "ОСП по работе с физическими лицами №2 г.Петрозаводска 185910, Республика Карелия, г.Петрозаводск, ул.Красная, д.33",
                        "bailiff": "ЗВУКОВА М. Д. +7(8142)76-08-74<br>+7(8142)76-08-74<br>+7(8142)76-05-55",
                        "ip_end": ""
                    },
                    {
                        "name": "НИКИТИН АЛЕКСЕЙ ВЛАДИМИРОВИЧ 06.11.1974 НЕИЗВЕСТНО",
                        "exe_production": "92392/19/10020-ИП от 26.06.2019 9272/20/10020-СД",
                        "details": "Акт по делу об административном правонарушении от 13.02.2019 № 2019251000630 ОТДЕЛ ПОЛИЦИИ №1 ПО ГОРОДУ ПЕТРОЗАВОДСКУ РЕСПУБЛИКИ КАРЕЛИЯ",
                        "subject": "Иной штраф ОВД: 500 руб.",
                        "department": "ОСП по работе с физическими лицами №2 г.Петрозаводска 185910, Республика Карелия, г.Петрозаводск, ул.Красная, д.33",
                        "bailiff": "ЗВУКОВА М. Д. +7(8142)76-08-74<br>+7(8142)76-08-74<br>+7(8142)76-05-55",
                        "ip_end": ""
                    },
                    {
                        "name": "НИКИТИН АЛЕКСЕЙ ВЛАДИМИРОВИЧ 06.11.1974 Г. ПЕТРОЗАВОДСК",
                        "exe_production": "94703/19/10020-ИП от 01.07.2019",
                        "details": "Акт по делу об административном правонарушении от 19.04.2019 № 32210019190000018012 СУДЕБНЫЙ УЧАСТОК № 2 Г. ПЕТРОЗАВОДСКА",
                        "subject": "Штраф как вид наказания по делам об АП, назначенный судом по протоколу должностного лица ФССП Штраф СПИ: 1000 руб.",
                        "department": "ОСП по работе с физическими лицами №2 г.Петрозаводска 185910, Республика Карелия, г.Петрозаводск, ул.Красная, д.33",
                        "bailiff": "ДЕРКАЧЕВА Ю. В. +7(8142)76-05-93<br>+7(8142)76-08-74<br>+7(8142)76-05-55",
                        "ip_end": ""
                    },
                    {
                        "name": "НИКИТИН АЛЕКСЕЙ ВЛАДИМИРОВИЧ 06.11.1974 Г. ПЕТРОЗАВОДСК",
                        "exe_production": "153179/19/10020-ИП от 11.10.2019",
                        "details": "Исполнительный лист от 07.10.2019 № ФС 030378229 ПЕТРОЗАВОДСКИЙ ГОРОДСКОЙ СУД",
                        "subject": "Госпошлина, присужденная судом: 300 руб.",
                        "department": "ОСП по работе с физическими лицами №2 г.Петрозаводска 185910, Республика Карелия, г.Петрозаводск, ул.Красная, д.33",
                        "bailiff": "ДЕРКАЧЕВА Ю. В. +7(8142)76-05-93<br>+7(8142)76-08-74<br>+7(8142)76-05-55",
                        "ip_end": ""
                    },
                    {
                        "name": "НИКИТИН АЛЕКСЕЙ ВЛАДИМИРОВИЧ 06.11.1974 Г. ПЕТРОЗАВОДСК",
                        "exe_production": "189017/19/10020-ИП от 02.12.2019 9272/20/10020-СД",
                        "details": "Судебный приказ от 10.10.2019 № СП2-3215/2019-2 СУДЕБНЫЙ УЧАСТОК № 2 Г. ПЕТРОЗАВОДСКА",
                        "subject": "Задолженность по платежам за газ, тепло и электроэнергию: 29097.97 руб.",
                        "department": "ОСП по работе с физическими лицами №2 г.Петрозаводска 185910, Республика Карелия, г.Петрозаводск, ул.Красная, д.33",
                        "bailiff": "ЗВУКОВА М. Д. +7(8142)76-08-74<br>+7(8142)76-08-74<br>+7(8142)76-05-55",
                        "ip_end": ""
                    },
                    {
                        "name": "НИКИТИН АЛЕКСЕЙ ВЛАДИМИРОВИЧ 06.11.1947 РЕСПУБЛИКА КАРЕЛИЯ, ПЕТРОЗАВОДСК",
                        "exe_production": "201227/19/10020-ИП от 23.12.2019 9272/20/10020-СД",
                        "details": "Постановление судебного пристава-исполнителя от 22.03.2018 № 10020/18/89866 Постановление о взыскании исполнительского сбора ОСП ПО РАБОТЕ С ФИЗИЧЕСКИМИ ЛИЦАМИ №2 Г.ПЕТРОЗАВОДСКА",
                        "subject": "Исполнительский сбор: 1000 руб.",
                        "department": "ОСП по работе с физическими лицами №2 г.Петрозаводска 185910, Республика Карелия, г.Петрозаводск, ул.Красная, д.33",
                        "bailiff": "ЗВУКОВА М. Д. +7(8142)76-08-74<br>+7(8142)76-08-74<br>+7(8142)76-05-55",
                        "ip_end": ""
                    },
                    {
                        "name": "НИКИТИН АЛЕКСЕЙ ПЕТРОВИЧ 30.05.1975 СССР ГОР. ПЕТРОЗАВОДСК",
                        "exe_production": "159655/19/10020-ИП от 23.10.2019 159655/19/10020-СД",
                        "details": "Судебный приказ от 02.11.2018 № СП 2А-3026/2018-9 СУДЕБНЫЙ УЧАСТОК № 9 Г. ПЕТРОЗАВОДСКА",
                        "subject": "Взыскание налогов и сборов, включая пени: 4006.21 руб.",
                        "department": "ОСП по работе с физическими лицами №2 г.Петрозаводска 185910, Республика Карелия, г.Петрозаводск, ул.Красная, д.33",
                        "bailiff": "ПОВЕЛИХИНА Н. П. +7(8142)76-38-11<br>+7(8142)76-08-74<br>+7(8142)76-05-55",
                        "ip_end": ""
                    },
                    {
                        "name": "НИКИТИН АЛЕКСЕЙ ПЕТРОВИЧ 30.05.1975 185000, РОССИЯ, Г. ПЕТРОЗАВОДСК",
                        "exe_production": "184825/19/10020-ИП от 26.11.2019",
                        "details": "Исполнительный лист от 18.10.2019 № ВС085332237 СУДЕБНЫЙ УЧАСТОК № 9 Г. ПЕТРОЗАВОДСКА",
                        "subject": "Госпошлина, присужденная судом: 162.52 руб.",
                        "department": "ОСП по работе с физическими лицами №2 г.Петрозаводска 185910, Республика Карелия, г.Петрозаводск, ул.Красная, д.33",
                        "bailiff": "ПОВЕЛИХИНА Н. П. +7(8142)76-38-11<br>+7(8142)76-08-74<br>+7(8142)76-05-55",
                        "ip_end": ""
                    },
                    {
                        "name": "НИКИТИН АЛЕКСЕЙ ВЛАДИМИРОВИЧ 06.11.1974 Г. ПЕТРОЗАВОДСК",
                        "exe_production": "9272/20/10020-ИП от 23.01.2020 9272/20/10020-СД",
                        "details": "Судебный приказ от 26.01.2016 № СП-3146/2015-2 СУДЕБНЫЙ УЧАСТОК № 2 Г. ПЕТРОЗАВОДСКА",
                        "subject": "Задолженность по платежам за газ, тепло и электроэнергию: 7055.54 руб.",
                        "department": "ОСП по работе с физическими лицами №2 г.Петрозаводска 185910, Республика Карелия, г.Петрозаводск, ул.Красная, д.33",
                        "bailiff": "ЗВУКОВА М. Д. +7(8142)76-08-74<br>+7(8142)76-08-74<br>+7(8142)76-05-55",
                        "ip_end": ""
                    },
                    {
                        "name": "НИКИТИН АЛЕКСЕЙ ЕГОРОВИЧ 08.08.1930",
                        "exe_production": "15819/20/10020-ИП от 30.01.2020",
                        "details": "Судебный приказ от 13.08.2019 № СП2-2320/2019-2 СУДЕБНЫЙ УЧАСТОК № 2 Г. ПЕТРОЗАВОДСКА",
                        "subject": "Задолженность по платежам за жилую площадь, коммунальные платежи, включая пени: 3739.32 руб.",
                        "department": "ОСП по работе с физическими лицами №2 г.Петрозаводска 185910, Республика Карелия, г.Петрозаводск, ул.Красная, д.33",
                        "bailiff": "ОМЕЛЬКИНА О. Н. +7(8142)76-56-59<br>+7(8142)76-08-74<br>+7(8142)76-05-55",
                        "ip_end": ""
                    },
                    {
                        "name": "НИКИТИН АЛЕКСЕЙ АЛЕКСАНДРОВИЧ 05.07.1971 185000, РОССИЯ, Г. ПЕТРОЗАВОДСК",
                        "exe_production": "47909/20/10020-ИП от 01.04.2020",
                        "details": "Судебный приказ от 04.03.2020 № СП2-137/2020-7 СУДЕБНЫЙ УЧАСТОК № 7 Г. ПЕТРОЗАВОДСКА",
                        "subject": "Задолженность по кредитным платежам (кроме ипотеки): 121662.6 руб.",
                        "department": "ОСП по работе с физическими лицами №2 г.Петрозаводска 185910, Республика Карелия, г.Петрозаводск, ул.Красная, д.33",
                        "bailiff": "ГРИГОРЬЕВА Н. В. +7(8142)76-05-93<br>+7(8142)76-08-74<br>+7(8142)76-05-55",
                        "ip_end": ""
                    },
                    {
                        "name": "НИКИТИН АЛЕКСЕЙ ВЛАДИМИРОВИЧ 06.11.1974 НЕИЗВЕСТНО",
                        "exe_production": "139070/19/10020-ИП от 16.09.2019 9272/20/10020-СД",
                        "details": "Акт по делу об административном правонарушении от 16.06.2019 № Б/Н ОТДЕЛ ПОЛИЦИИ №3 ПО ГОРОДУ ПЕТРОЗАВОДСКУ РЕСПУБЛИКИ КАРЕЛИЯ",
                        "subject": "Иной штраф ОВД: 500 руб.",
                        "department": "ОСП по работе с физическими лицами №2 г.Петрозаводска 185910, Республика Карелия, г.Петрозаводск, ул.Красная, д.33",
                        "bailiff": "ЗВУКОВА М. Д. +7(8142)76-08-74<br>+7(8142)76-08-74<br>+7(8142)76-05-55",
                        "ip_end": ""
                    },
                    {
                        "name": "НИКИТИН АЛЕКСЕЙ ВЛАДИМИРОВИЧ 06.11.1974 Г. ПЕТРОЗАВОДСК",
                        "exe_production": "21549/20/10020-ИП от 11.02.2020",
                        "details": "Акт по делу об административном правонарушении от 19.11.2019 № 5-1672/2019-2 СУДЕБНЫЙ УЧАСТОК № 2 Г. ПЕТРОЗАВОДСКА",
                        "subject": "Штраф как вид наказания по делам об АП, назначенный судом (за исключением дел по протоколам ФССП): 1000 руб.",
                        "department": "ОСП по работе с физическими лицами №2 г.Петрозаводска 185910, Республика Карелия, г.Петрозаводск, ул.Красная, д.33",
                        "bailiff": "ДЕРКАЧЕВА Ю. В. +7(8142)76-05-93<br>+7(8142)76-08-74<br>+7(8142)76-05-55",
                        "ip_end": ""
                    },
                    {
                        "name": "НИКИТИН АЛЕКСЕЙ ПЕТРОВИЧ 30.05.1975 СССР ГОР. ПЕТРОЗАВОДСК",
                        "exe_production": "74159/20/10020-ИП от 05.06.2020",
                        "details": "Судебный приказ от 18.10.2019 № СП2А-3047/2019-9 СУДЕБНЫЙ УЧАСТОК № 9 Г. ПЕТРОЗАВОДСКА",
                        "subject": "Взыскание налогов и сборов, включая пени: 4796.78 руб.",
                        "department": "ОСП по работе с физическими лицами №2 г.Петрозаводска 185910, Республика Карелия, г.Петрозаводск, ул.Красная, д.33",
                        "bailiff": "ПОВЕЛИХИНА Н. П. +7(8142)76-38-11<br>+7(8142)76-08-74<br>+7(8142)76-05-55",
                        "ip_end": ""
                    },
                    {
                        "name": "НИКИТИН АЛЕКСЕЙ АЛЕКСАНДРОВИЧ 28.10.1976 РОССИЯ, ПЕТРОЗАВОДСК",
                        "exe_production": "72901/20/10020-ИП от 03.06.2020",
                        "details": "Судебный приказ от 31.10.2019 № 2А-3951/2019-2 СУДЕБНЫЙ УЧАСТОК № 2 Г. ПЕТРОЗАВОДСКА",
                        "subject": "Взыскание налогов и сборов, включая пени: 3680.33 руб.",
                        "department": "ОСП по работе с физическими лицами №2 г.Петрозаводска 185910, Республика Карелия, г.Петрозаводск, ул.Красная, д.33",
                        "bailiff": "ФЕСЕНКО В. М. +7(8142)76-05-93<br>+7(8142)76-08-74<br>+7(8142)76-05-55",
                        "ip_end": ""
                    },
                    {
                        "name": "НИКИТИН АЛЕКСЕЙ ВЛАДИМИРОВИЧ 06.11.1974 Г. ПЕТРОЗАВОДСК",
                        "exe_production": "96463/20/10020-ИП от 07.07.2020",
                        "details": "Судебный приказ от 17.04.2016 № СП2-618/2016-2 СУДЕБНЫЙ УЧАСТОК № 2 Г. ПЕТРОЗАВОДСКА",
                        "subject": "Задолженность по платежам за жилую площадь, коммунальные платежи, включая пени: 4089.1 руб.",
                        "department": "ОСП по работе с физическими лицами №2 г.Петрозаводска 185910, Республика Карелия, г.Петрозаводск, ул.Красная, д.33",
                        "bailiff": "ЗВУКОВА М. Д. +7(8142)76-08-74<br>+7(8142)76-08-74<br>+7(8142)76-05-55",
                        "ip_end": ""
                    },
                    {
                        "name": "НИКИТИН АЛЕКСЕЙ АЛЕКСАНДРОВИЧ 28.10.1976 РОССИЯ, Г. ПЕТРОЗАВОДСК",
                        "exe_production": "19473/17/10021-ИП от 30.08.2010",
                        "details": "Судебный приказ от 01.08.2008 № СП-1307/08-6 СУДЕБНЫЙ УЧАСТОК № 6 Г. ПЕТРОЗАВОДСКА",
                        "subject": "Задолженность по ИД: 278264.25 руб.",
                        "department": "ОСП по исполнению исполнительных документов по взысканию алиментных платежей по г. Петрозаводску и Прионежскому району 185910, Республика Карелия, г.Петрозаводск, ул.Красная, д.33",
                        "bailiff": "АКИМОВА А. А. +7(8142)78-51-16<br>+7(8142)76-05-60<br>+7(8142)76-05-55",
                        "ip_end": ""
                    },
                    {
                        "name": "НИКИТИН АЛЕКСЕЙ ПЕТРОВИЧ 30.05.1975 Г.ПЕТРОЗАВОДСК, КАССР",
                        "exe_production": "20359/17/10021-ИП от 12.05.2015",
                        "details": "Судебный приказ от 28.11.2014 № СП-2223/2014-10 МИРОВОЙ СУДЬЯ С/У № 10 Г. ПЕТРОЗАВОДСКА",
                        "subject": "Задолженность по ИД: 261836.97 руб.",
                        "department": "ОСП по исполнению исполнительных документов по взысканию алиментных платежей по г. Петрозаводску и Прионежскому району 185910, Республика Карелия, г.Петрозаводск, ул.Красная, д.33",
                        "bailiff": "АКИМОВА А. А. +7(8142)78-51-16<br>+7(8142)76-05-60<br>+7(8142)76-05-55",
                        "ip_end": ""
                    },
                    {
                        "name": "НИКИТИН АЛЕКСЕЙ ВЛАДИМИРОВИЧ 06.11.1974 185000, РОССИЯ, Г. ПЕТРОЗАВОДСК",
                        "exe_production": "28832/17/10021-ИП от 25.02.2011",
                        "details": "Исполнительный лист от 07.05.2010 № 2-171/2010-2 СУДЕБНЫЙ УЧАСТОК № 4 Г. ПЕТРОЗАВОДСКА",
                        "subject": "Задолженность по ИД: 790525.3 руб.",
                        "department": "ОСП по исполнению исполнительных документов по взысканию алиментных платежей по г. Петрозаводску и Прионежскому району 185910, Республика Карелия, г.Петрозаводск, ул.Красная, д.33",
                        "bailiff": "КОЗИЦИНА Р. П. +7(8142)78-51-16<br>+7(8142)76-05-60<br>+7(8142)76-05-55",
                        "ip_end": ""
                    },
                    {
                        "name": "НИКИТИН АЛЕКСЕЙ ВЛАДИМИРОВИЧ 06.11.1974 185000, РОССИЯ, Г. ПЕТРОЗАВОДСК",
                        "exe_production": "1033/19/10021-ИП от 01.02.2019",
                        "details": "Акт по делу об административном правонарушении от 16.01.2019 № 32210021190004853011 СУДЕБНЫЙ УЧАСТОК № 2 Г. ПЕТРОЗАВОДСКА",
                        "subject": "Административное наказание в виде обязательных работ, наложенных судом по протоколу должностного лица ФССП России",
                        "department": "ОСП по исполнению исполнительных документов по взысканию алиментных платежей по г. Петрозаводску и Прионежскому району 185910, Республика Карелия, г.Петрозаводск, ул.Красная, д.33",
                        "bailiff": "КОЗИЦИНА Р. П. +7(8142)78-51-16<br>+7(8142)76-05-60<br>+7(8142)76-05-55",
                        "ip_end": ""
                    },
                    {
                        "name": "НИКИТИН АЛЕКСЕЙ НИКОЛАЕВИЧ 02.02.1982 Г. ПЕТРОЗАВОДСК",
                        "exe_production": "2164/20/10021-ИП от 15.11.2019",
                        "details": "Судебный приказ от 28.01.2009 № СП-48/2009-2 СУДЕБНЫЙ УЧАСТОК № 2 Г. ПЕТРОЗАВОДСКА",
                        "subject": "Задолженность по ИД: 9878.3 руб.",
                        "department": "ОСП по исполнению исполнительных документов по взысканию алиментных платежей по г. Петрозаводску и Прионежскому району 185910, Республика Карелия, г.Петрозаводск, ул.Красная, д.33",
                        "bailiff": "КОЗИЦИНА Р. П. +7(8142)78-51-16<br>+7(8142)76-05-60<br>+7(8142)76-05-55",
                        "ip_end": ""
                    },
                    {
                        "name": "НИКИТИН АЛЕКСЕЙ ИВАНОВИЧ 24.05.1983 РЕСПУБЛИКА КАРЕЛИЯ",
                        "exe_production": "39678/20/10005-ИП от 23.07.2020 33530/17/10005-СД",
                        "details": "Акт по делу об административном правонарушении от 08.05.2020 № 18810010190000486393 ОБДПС УМВД РОССИИ ПО Г. ПЕТРОЗАВОДСКУ",
                        "subject": "Штраф ГИБДД: 500 руб.",
                        "department": "ОСП по Кондопожскому району 186200, Республика Карелия, г.Кондопога, пр.Калинина, д.11б",
                        "bailiff": "ВАСИЛЬЕВА А. А. +7(81451)7-36-74<br>+7(81451)7-81-10<br>",
                        "ip_end": ""
                    },
                    {
                        "name": "НИКИТИН АЛЕКСЕЙ ИВАНОВИЧ 24.05.1983 КАРЕЛИЯ РЕСП, КОНДОПОЖСКИЙ Р-Н, С КОНЧЕЗЕРО",
                        "exe_production": "15200/17/10005-ИП от 07.07.2017 33530/17/10005-СД",
                        "details": "Судебный приказ от 24.04.2017 № 2-606/2017 Постановление о взыскании исполнительского сбора СУДЕБНЫЙ УЧАСТОК № 2 КОНДОПОЖСКОГО РАЙОНА",
                        "subject": "Взыскание налогов и сборов, включая пени Исполнительский сбор: 2204.64 руб.",
                        "department": "ОСП по Кондопожскому району 186200, Республика Карелия, г.Кондопога, пр.Калинина, д.11б",
                        "bailiff": "ВАСИЛЬЕВА А. А. +7(81451)7-36-74<br>+7(81451)7-81-10<br>",
                        "ip_end": ""
                    },
                    {
                        "name": "НИКИТИН АЛЕКСЕЙ АНАТОЛЬЕВИЧ 18.10.1976 РОССИЯ, РЕСП. КАРЕЛИЯ, Г. КОНДОПОГА",
                        "exe_production": "18505/17/10005-ИП от 22.08.2017 3145/17/10005-СД",
                        "details": "Судебный приказ от 05.11.2014 № 2-1534/2014 СУДЕБНЫЙ УЧАСТОК № 2 КОНДОПОЖСКОГО РАЙОНА",
                        "subject": "Задолженность по платежам за жилую площадь, коммунальные платежи, включая пени",
                        "department": "ОСП по Кондопожскому району 186200, Республика Карелия, г.Кондопога, пр.Калинина, д.11б",
                        "bailiff": "ДРУЖКОВА Е. С. +7(81451)7-98-67<br>+7(81451)7-81-10<br>",
                        "ip_end": "2017-08-30, 46, 1, 4"
                    },
                    {
                        "name": "НИКИТИН АЛЕКСЕЙ ИВАНОВИЧ 24.05.1983 РЕСПУБЛИКА КАРЕЛИЯ",
                        "exe_production": "24603/17/10005-ИП от 26.10.2017",
                        "details": "Акт по делу об административном правонарушении от 23.06.2017 № 18810010150001932153 ОГИБДД ОМВД РОССИИ ПО ОЛОНЕЦКОМУ РАЙОНУ",
                        "subject": "Штраф ГИБДД",
                        "department": "ОСП по Кондопожскому району 186200, Республика Карелия, г.Кондопога, пр.Калинина, д.11б",
                        "bailiff": "КАЛИНИНА Е. Г. +7(81451)7-36-74<br>+7(81451)7-81-10<br>",
                        "ip_end": "2017-11-29, 46, 1, 4"
                    },
                    {
                        "name": "НИКИТИН АЛЕКСЕЙ ИВАНОВИЧ 24.05.1983 РЕСПУБЛИКА КАРЕЛИЯ",
                        "exe_production": "28228/17/10005-ИП от 20.11.2017",
                        "details": "Акт по делу об административном правонарушении от 10.05.2016 № 18810010140001950020 ОГИБДД ОМВД РОССИИ ПО ПРИОНЕЖСКОМУ РАЙОНУ",
                        "subject": "Штраф ГИБДД",
                        "department": "ОСП по Кондопожскому району 186200, Республика Карелия, г.Кондопога, пр.Калинина, д.11б",
                        "bailiff": "КАЛИНИНА Е. Г. +7(81451)7-36-74<br>+7(81451)7-81-10<br>",
                        "ip_end": "2017-11-29, 46, 1, 4"
                    },
                    {
                        "name": "НИКИТИН АЛЕКСЕЙ ИВАНОВИЧ 24.05.1983 РЕСПУБЛИКА КАРЕЛИЯ С. КОНЧЕЗЕРО КОНДО",
                        "exe_production": "33059/17/10005-ИП от 25.12.2017",
                        "details": "Акт по делу об административном правонарушении от 03.10.2017 № 18810110171003017406 ЦАФАП ГИБДД МВД ПО РЕСПУБЛИКЕ КАРЕЛИЯ",
                        "subject": "Штраф ГИБДД",
                        "department": "ОСП по Кондопожскому району 186200, Республика Карелия, г.Кондопога, пр.Калинина, д.11б",
                        "bailiff": "КАЛИНИНА Е. Г. +7(81451)7-36-74<br>+7(81451)7-81-10<br>",
                        "ip_end": "2017-12-27, 46, 1, 4"
                    },
                    {
                        "name": "НИКИТИН АЛЕКСЕЙ АНАТОЛЬЕВИЧ 18.10.1976 НОВГОРОДСКАЯ ОБЛ., ОКУЛОВСКИЙ Р-Н, НОВОСЕЛИЦЫ Д.",
                        "exe_production": "10921/18/10005-ИП от 09.04.2018",
                        "details": "Судебный приказ от 05.11.2014 № 2-1594/2014 СУДЕБНЫЙ УЧАСТОК № 2 КОНДОПОЖСКОГО РАЙОНА",
                        "subject": "Задолженность по платежам за жилую площадь, коммунальные платежи, включая пени",
                        "department": "ОСП по Кондопожскому району 186200, Республика Карелия, г.Кондопога, пр.Калинина, д.11б",
                        "bailiff": "МЯКИНЕН А. А. +7(81451)7-36-74<br>+7(81451)7-81-10<br>",
                        "ip_end": "2018-04-13, 46, 1, 4"
                    },
                    {
                        "name": "НИКИТИН АЛЕКСЕЙ ИВАНОВИЧ 24.05.1983 СССР КАРЕЛЬСКАЯ АССР КОНДОПОЖСКИЙ Р-Н С. КОНЧЕЗЕРО",
                        "exe_production": "15988/18/10005-ИП от 31.05.2018 33530/17/10005-СД",
                        "details": "Судебный приказ от 19.03.2018 № 2-579/2018 Постановление о взыскании исполнительского сбора СУДЕБНЫЙ УЧАСТОК № 2 КОНДОПОЖСКОГО РАЙОНА",
                        "subject": "Взыскание налогов и сборов, включая пени Исполнительский сбор: 2381.79 руб.",
                        "department": "ОСП по Кондопожскому району 186200, Республика Карелия, г.Кондопога, пр.Калинина, д.11б",
                        "bailiff": "ВАСИЛЬЕВА А. А. +7(81451)7-36-74<br>+7(81451)7-81-10<br>",
                        "ip_end": ""
                    },
                    {
                        "name": "НИКИТИН АЛЕКСЕЙ ИВАНОВИЧ 24.05.1983 РЕСП. КАРЕЛИЯ, Г. КОНДОПОГА",
                        "exe_production": "41026/18/10005-ИП от 26.11.2018 33530/17/10005-СД",
                        "details": "Судебный приказ от 08.10.2018 № 2-2021/2018 Постановление о взыскании исполнительского сбора СУДЕБНЫЙ УЧАСТОК № 2 КОНДОПОЖСКОГО РАЙОНА",
                        "subject": "Взыскание налогов и сборов, включая пени Исполнительский сбор: 966.43 руб.",
                        "department": "ОСП по Кондопожскому району 186200, Республика Карелия, г.Кондопога, пр.Калинина, д.11б",
                        "bailiff": "ВАСИЛЬЕВА А. А. +7(81451)7-36-74<br>+7(81451)7-81-10<br>",
                        "ip_end": ""
                    },
                    {
                        "name": "НИКИТИН АЛЕКСЕЙ ИВАНОВИЧ 24.05.1983 РЕСП. КАРЕЛИЯ, КОНДОПОЖСКИЙ Р-Н, С. КОНЧЕЗЕРО",
                        "exe_production": "50279/19/10005-ИП от 03.06.2019 33530/17/10005-СД",
                        "details": "Судебный приказ от 26.12.2018 № 2-2488/2018 Постановление о взыскании исполнительского сбора СУДЕБНЫЙ УЧАСТОК № 2 КОНДОПОЖСКОГО РАЙОНА",
                        "subject": "Задолженность по кредитным платежам (кроме ипотеки): 168166.07 руб. Исполнительский сбор: 11376.48 руб.",
                        "department": "ОСП по Кондопожскому району 186200, Республика Карелия, г.Кондопога, пр.Калинина, д.11б",
                        "bailiff": "ВАСИЛЬЕВА А. А. +7(81451)7-36-74<br>+7(81451)7-81-10<br>",
                        "ip_end": ""
                    },
                    {
                        "name": "НИКИТИН АЛЕКСЕЙ АНАТОЛЬЕВИЧ 18.10.1976 РОССИЯ, РЕСП. КАРЕЛИЯ, Г. КОНДОПОГА",
                        "exe_production": "86006/19/10005-ИП от 09.12.2019 86006/19/10005-СД",
                        "details": "Исполнительный лист от 02.02.2017 № 013945986 КОНДОПОЖСКИЙ ГОРОДСКОЙ СУД",
                        "subject": "Процессуальные издержки в доход государства: 3234 руб.",
                        "department": "ОСП по Кондопожскому району 186200, Республика Карелия, г.Кондопога, пр.Калинина, д.11б",
                        "bailiff": "ФОМИНА А. П. +7(81451)7-54-47<br>+7(81451)7-81-10<br>",
                        "ip_end": ""
                    },
                    {
                        "name": "НИКИТИН АЛЕКСЕЙ ИВАНОВИЧ 24.05.1983 РЕСП. КАРЕЛИЯ, Г. КОНДОПОГА",
                        "exe_production": "75976/19/10005-ИП от 22.10.2019 33530/17/10005-СД",
                        "details": "Судебный приказ от 16.08.2019 № 2-2126/2019 СУДЕБНЫЙ УЧАСТОК № 2 КОНДОПОЖСКОГО РАЙОНА",
                        "subject": "Взыскание налогов и сборов, включая пени: 2839.08 руб.",
                        "department": "ОСП по Кондопожскому району 186200, Республика Карелия, г.Кондопога, пр.Калинина, д.11б",
                        "bailiff": "ВАСИЛЬЕВА А. А. +7(81451)7-36-74<br>+7(81451)7-81-10<br>",
                        "ip_end": ""
                    },
                    {
                        "name": "НИКИТИН АЛЕКСЕЙ АНАТОЛЬЕВИЧ 18.10.1976 РОССИЯ, РЕСП. КАРЕЛИЯ, Г. КОНДОПОГА",
                        "exe_production": "13725/20/10005-ИП от 17.03.2020 86006/19/10005-СД",
                        "details": "Судебный приказ от 05.11.2014 № 2-1594/2014 СУДЕБНЫЙ УЧАСТОК № 2 КОНДОПОЖСКОГО РАЙОНА",
                        "subject": "Задолженность по платежам за жилую площадь, коммунальные платежи, включая пени: 8515.9 руб.",
                        "department": "ОСП по Кондопожскому району 186200, Республика Карелия, г.Кондопога, пр.Калинина, д.11б",
                        "bailiff": "ФОМИНА А. П. +7(81451)7-54-47<br>+7(81451)7-81-10<br>",
                        "ip_end": ""
                    },
                    {
                        "name": "НИКИТИН АЛЕКСЕЙ АЛЕКСАНДРОВИЧ 03.06.1984 186930, РОССИЯ, РЕСП. КАРЕЛИЯ, Г. КОСТОМУКША",
                        "exe_production": "7471/19/10006-ИП от 01.03.2019 7471/19/10006-СД",
                        "details": "Судебный приказ от 15.11.2018 № 2-1479/2018 СУДЕБНЫЙ УЧАСТОК № 1 Г. КОСТОМУКША",
                        "subject": "Иные взыскания имущественного характера не в бюджеты РФ: 16575 руб.",
                        "department": "ОСП по г.Костомукше 186930, Республика Карелия, г.Костомукша, ул.Ленина, д.17а",
                        "bailiff": "МУГИНОВА М. Т. +7(81459)7-43-02<br>+7(81459)5-13-78<br>",
                        "ip_end": ""
                    },
                    {
                        "name": "НИКИТИН АЛЕКСЕЙ АЛЕКСАНДРОВИЧ 03.06.1984 Г.КОСТОМУКША",
                        "exe_production": "41676/19/10006-ИП от 05.11.2019 7471/19/10006-СД",
                        "details": "Акт по делу об административном правонарушении от 01.08.2019 № 5-109/2019 КОСТОМУКШСКИЙ ГОРОДСКОЙ СУД",
                        "subject": "Штраф как вид наказания по делам об АП, назначенный судом (за исключением дел по протоколам ФССП): 999.96 руб.",
                        "department": "ОСП по г.Костомукше 186930, Республика Карелия, г.Костомукша, ул.Ленина, д.17а",
                        "bailiff": "МУГИНОВА М. Т. +7(81459)7-43-02<br>+7(81459)5-13-78<br>",
                        "ip_end": ""
                    },
                    {
                        "name": "НИКИТИН АЛЕКСЕЙ АЛЕКСАНДРОВИЧ 03.06.1984 Г.КОСТОМУКША",
                        "exe_production": "16050/20/10006-ИП от 01.06.2020 7471/19/10006-СД",
                        "details": "Акт по делу об административном правонарушении от 01.08.2019 № 2019180001767 ОМВД РОССИИ ПО Г. КОСТОМУКШЕ",
                        "subject": "Иной штраф ОВД: 499.97 руб.",
                        "department": "ОСП по г.Костомукше 186930, Республика Карелия, г.Костомукша, ул.Ленина, д.17а",
                        "bailiff": "МУГИНОВА М. Т. +7(81459)7-43-02<br>+7(81459)5-13-78<br>",
                        "ip_end": ""
                    },
                    {
                        "name": "НИКИТИН АЛЕКСЕЙ АЛЕКСАНДРОВИЧ 03.06.1984 186930, РОССИЯ, РЕСП. КАРЕЛИЯ, Г. КОСТОМУКША",
                        "exe_production": "24355/20/10006-ИП от 21.07.2020 7471/19/10006-СД",
                        "details": "Судебный приказ от 13.05.2020 № 2-718/2020 СУДЕБНЫЙ УЧАСТОК № 1 Г. КОСТОМУКША",
                        "subject": "Иные взыскания имущественного характера не в бюджеты РФ: 1619 руб.",
                        "department": "ОСП по г.Костомукше 186930, Республика Карелия, г.Костомукша, ул.Ленина, д.17а",
                        "bailiff": "МУГИНОВА М. Т. +7(81459)7-43-02<br>+7(81459)5-13-78<br>",
                        "ip_end": ""
                    },
                    {
                        "name": "НИКИТИН АЛЕКСЕЙ КЛАВДИЕВИЧ 15.09.1974 РЕСП. КАРЕЛИЯ, СЕГЕЖСКИЙ Р-Н, ПОЛГА Д.",
                        "exe_production": "9989/18/10016-ИП от 22.02.2018 26292/17/10016-СД",
                        "details": "Судебный приказ от 13.11.2017 № 2-4100/2017 СУДЕБНЫЙ УЧАСТОК № 3 СЕГЕЖСКОГО РАЙОНА",
                        "subject": "Задолженность по кредитным платежам (кроме ипотеки)",
                        "department": "ОСП по Сегежскому району 186420, Республика Карелия, г.Сегежа, ул.Гражданская, 4а",
                        "bailiff": "ЯКОВЛЕВА М. О. +7(814)314-24-07<br>+7(81431)4-30-19<br>",
                        "ip_end": ""
                    },
                    {
                        "name": "НИКИТИН АЛЕКСЕЙ КЛАВДИЕВИЧ 15.09.1974 РЕСП. КАРЕЛИЯ, СЕГЕЖСКИЙ Р-Н, ПОЛГА Д.",
                        "exe_production": "16618/19/10016-ИП от 14.03.2019 26292/17/10016-СД",
                        "details": "Судебный приказ от 14.01.2019 № 2-141/2019 СУДЕБНЫЙ УЧАСТОК № 3 СЕГЕЖСКОГО РАЙОНА",
                        "subject": "Задолженность по кредитным платежам (кроме ипотеки): 36498.07 руб.",
                        "department": "ОСП по Сегежскому району 186420, Республика Карелия, г.Сегежа, ул.Гражданская, 4а",
                        "bailiff": "ЯКОВЛЕВА М. О. +7(814)314-24-07<br>+7(81431)4-30-19<br>",
                        "ip_end": ""
                    },
                    {
                        "name": "НИКИТИН АЛЕКСЕЙ АЛЕКСАНДРОВИЧ 24.09.1958 РЕСП. КАРЕЛИЯ, МЕДВЕЖЬЕГОРСКИЙ Р-Н, Г. МЕДВЕЖЬЕГОРСК",
                        "exe_production": "60364/20/10016-ИП от 12.08.2020",
                        "details": "Акт по делу об административном правонарушении от 14.05.2020 № 5-290/2020 СУДЕБНЫЙ УЧАСТОК № 2 СЕГЕЖСКОГО РАЙОНА",
                        "subject": "Штраф как вид наказания по делам об АП, назначенный судом (за исключением дел по протоколам ФССП)",
                        "department": "ОСП по Сегежскому району 186420, Республика Карелия, г.Сегежа, ул.Гражданская, 4а",
                        "bailiff": "СМИРНОВА Н. И. +7(81431)4-30-19<br>+7(81431)4-30-19<br>",
                        "ip_end": ""
                    },
                    {
                        "name": "НИКИТИН АЛЕКСЕЙ АНДРЕЕВИЧ 20.01.1999 Г. САНКТ-ПЕТЕРБУРГ",
                        "exe_production": "11420/20/10017-ИП от 27.03.2020",
                        "details": "Акт по делу об административном правонарушении от 16.12.2019 № 18810178191216095026 ЦАФАП В ОДД ГИБДД ГУ МВД РОССИИ ПО Г.СПБ И ЛО",
                        "subject": "Штраф ГИБДД: 3000 руб.",
                        "department": "ОСП по г.Сортавала 186750, Республика Карелия, г.Сортавала, ул.Карельская, д.42",
                        "bailiff": "ЧЕРПИТА А. В. +7(81430)4-66-67<br>+7(81430)4-68-44<br>",
                        "ip_end": ""
                    },
                    {
                        "name": "НИКИТИН АЛЕКСЕЙ ОКТЯБРИНОВИЧ 29.09.1958 ВОЛОГОДСКАЯ ОБЛ., ЧЕРЕПОВЕЦКИЙ Р-Н, ШУКЛИНО Д.",
                        "exe_production": "805/18/10008-ИП от 18.01.2018 805/18/10008-СД",
                        "details": "Судебный приказ от 13.11.2017 № 2-2219/2017 СУДЕБНЫЙ УЧАСТОК № 1 МЕДВЕЖЬЕГОРСКОГО РАЙОНА",
                        "subject": "Задолженность по кредитным платежам (кроме ипотеки)",
                        "department": "ОСП по Медвежьегорскому району 186352, Республика Карелия, г.Медвежьегорск, ул.Онежская, д.6",
                        "bailiff": "БЕЛЯЕВ С. Н. +7(81434)5-22-62<br>+7(81434)5-80-65<br>",
                        "ip_end": "2018-09-11, 47, 1, 7"
                    },
                    {
                        "name": "НИКИТИН АЛЕКСЕЙ ОКТЯБРИНОВИЧ 29.09.1958 ВОЛОГОДСКАЯ ОБЛ., ЧЕРЕПОВЕЦКИЙ Р-Н, ДЕР. ШУЛМА",
                        "exe_production": "3656/18/10008-ИП от 21.02.2018 805/18/10008-СД",
                        "details": "Судебный приказ от 13.11.2017 № СП2-4028/2017-1 СУДЕБНЫЙ УЧАСТОК № 1 Г. ПЕТРОЗАВОДСКА",
                        "subject": "Задолженность по кредитным платежам (кроме ипотеки)",
                        "department": "ОСП по Медвежьегорскому району 186352, Республика Карелия, г.Медвежьегорск, ул.Онежская, д.6",
                        "bailiff": "БЕЛЯЕВ С. Н. +7(81434)5-22-62<br>+7(81434)5-80-65<br>",
                        "ip_end": "2018-09-11, 47, 1, 7"
                    },
                    {
                        "name": "НИКИТИН АЛЕКСЕЙ ОКТЯБРИНОВИЧ 29.09.1958 ВОЛОГОДСКАЯ ОБЛ., ЧЕРЕПОВЕЦКИЙ Р-Н, ДЕР. ШУЛМА",
                        "exe_production": "25054/18/10008-ИП от 17.09.2018",
                        "details": "Судебный приказ от 30.03.2018 № 2-6763/18-25 СУДЕБНЫЙ УЧАСТОК № 25 ЗАПАДНОГО ВНУТРИГОРОДСКОГО ОКРУГА Г. КРАСНОДАРА",
                        "subject": "Задолженность по кредитным платежам (кроме ипотеки)",
                        "department": "ОСП по Медвежьегорскому району 186352, Республика Карелия, г.Медвежьегорск, ул.Онежская, д.6",
                        "bailiff": "БЕЛЯЕВ С. Н. +7(81434)5-22-62<br>+7(81434)5-80-65<br>",
                        "ip_end": "2018-09-17, 47, 1, 7"
                    },
                    {
                        "name": "НИКИТИН АЛЕКСЕЙ АЛЕКСЕЕВИЧ 15.12.1967 ПОСЕЛОК ОКТЯБРЬСКИЙ КИРОВСКОГО РАЙОНА ТУЛЬСКОЙ ОБЛАСТИ",
                        "exe_production": "7625/19/10013-ИП от 16.05.2019",
                        "details": "Исполнительный лист от 07.05.2019 № 026182726 ПЕТРОЗАВОДСКИЙ ГОРОДСКОЙ СУД",
                        "subject": "Уголовный штраф за коррупционное преступление доп. вид наказ. (иной администратор дохода): 24993119.74 руб.",
                        "department": "МОСП по особым исполнительным производствам 185035, Россия, , , г. Петрозаводск, , ул. Красная (Центр р-н), д. 33, , ",
                        "bailiff": "МИХАЙЛОВА Р. Г. +7(8142)76-06-93<br>+7(8142)76-06-93<br>",
                        "ip_end": ""
                    },
                    {
                        "name": "НИКИТИН АЛЕКСЕЙ АНАТОЛЬЕВИЧ 18.10.1976 РОССИЯ, РЕСП. КАРЕЛИЯ, Г. КОНДОПОГА",
                        "exe_production": "14127/19/10013-ИП от 10.02.2017",
                        "details": "Исполнительный лист от 02.02.2017 № 013945987 Постановление о взыскании исполнительского сбора КОНДОПОЖСКИЙ ГОРОДСКОЙ СУД",
                        "subject": "Моральный вред, причиненный преступлением: 477581.72 руб. Исполнительский сбор: 35000 руб.",
                        "department": "МОСП по особым исполнительным производствам 185035, Россия, , , г. Петрозаводск, , ул. Красная (Центр р-н), д. 33, , ",
                        "bailiff": "МИХАЙЛОВА Р. Г. +7(8142)76-06-93<br>+7(8142)76-06-93<br>",
                        "ip_end": ""
                    },
                    {
                        "name": "НИКИТИН АЛЕКСЕЙ АНДРЕЕВИЧ 07.10.1993 РЕСП. КАРЕЛИЯ, ПРЯЖИНСКИЙ Р-Н, П. ЭССОЙЛА",
                        "exe_production": "2740/19/10014-ИП от 18.02.2019",
                        "details": "Судебный приказ от 10.09.2018 № СП-2-1911/2018 СУДЕБНЫЙ УЧАСТОК ПРЯЖИНСКОГО РАЙОНА",
                        "subject": "",
                        "department": "ОСП по Пряжинскому району 186120, Республика Карелия, п.Пряжа, ул.Строительная, д.6",
                        "bailiff": "ЗАХАРОВА А. И. +7(81456)3-15-32<br>+7(81456)3-15-32<br>",
                        "ip_end": "2019-03-30, 46, 1, 3"
                    },
                    {
                        "name": "НИКИТИН АЛЕКСЕЙ АНДРЕЕВИЧ 07.10.1993 РЕСП. КАРЕЛИЯ, ПРЯЖИНСКИЙ Р-Н, П. ЭССОЙЛА",
                        "exe_production": "2238/20/10014-ИП от 30.01.2020",
                        "details": "Судебный приказ от 02.10.2019 № СП-2-1952/2019 СУДЕБНЫЙ УЧАСТОК ПРЯЖИНСКОГО РАЙОНА",
                        "subject": "Задолженность по ИД: 1815.21 руб.",
                        "department": "ОСП по Пряжинскому району 186120, Республика Карелия, п.Пряжа, ул.Строительная, д.6",
                        "bailiff": "ЗАХАРОВА А. И. +7(81456)3-15-32<br>+7(81456)3-15-32<br>",
                        "ip_end": ""
                    }
                ]
            }
        ]
    }
}
